과제_3/register_file.v
// register_file.v
module register_file(/*AUTOARG*/
   // Outputs
   read_data1, read_data2,
   // Inputs
   clk, rst_n, write_en, write_addr, write_data, read_addr1,
   read_addr2
   );
   input       clk, rst_n;
   input       write_en;
   input [4:0] write_addr;
   input [31:0]	write_data;
   input [4:0]	read_addr1;
   input [4:0]	read_addr2;
   output [31:0] read_data1;
   output [31:0] read_data2;

   reg [31:0]	 regs [0:31];

   integer	 i;

   always @(posedge clk or negedge rst_n) begin
      if (!rst_n) begin
	 for (i = 0; i < 32; i = i + 1)
	    regs[i] <= 32'd0;
      end else if (write_en) begin
	    regs[write_addr] <= write_data;
	 end
   end

   assign read_data1 = regs[read_addr1];
   assign read_data2 = regs[read_addr2];

endmodule // register_file

과제_3/alu.v
// alu.v
module alu(/*AUTOARG*/
   // Outputs
   result,
   // Inputs
   a, b, F
   );
   input [31:0] a, b;
   input [2:0]	F;
   output reg [31:0] result;

   always @(*)
     begin
	case(F)
	  3'b000: result = a + b;
	  3'b001: result = a + 32'd1;
	  3'b010: result = a - b;
	  3'b011: result = a - 32'd1;
	  3'b100: result = a * b;
	  default: result = 32'd0;
	endcase // case (f)
     end
endmodule // alu

과제_3/processor.v
// processor.v
module processor(/*AUTOARG*/
   // Inputs
   clk, rst_n, mode, F, read_addr1, read_addr2, dest_addr, store_addr,
   store_data
   );
   input clk, rst_n;
   input mode;
   input [2:0] F;
   input [4:0] read_addr1;
   input [4:0] read_addr2;
   input [4:0] dest_addr;
   input [4:0] store_addr;
   input [31:0]	store_data;

   wire [31:0]	alu_result;
   wire [31:0]	rf_read_data1, rf_read_data2;
   reg [4:0]	write_addr; 
   reg [31:0]	write_data;
   reg		write_en;

   wire [31:0]	alu_a = rf_read_data1;
   wire [31:0]	alu_b = rf_read_data2;

   alu alu_A(/*AUTOINST*/
	     // Outputs
	     .result			(alu_result),
	     // Inputs
	     .a				(alu_a),
	     .b				(alu_b),
	     .F				(F));

   register_file register_file_A(/*AUTOINST*/
				 // Inputs
				 .clk			(clk),
				 .rst_n			(rst_n),
				 .write_en		(write_en),
				 .write_addr		(write_addr),
				 .write_data		(write_data),
				 .read_addr1		(read_addr1),
				 .read_addr2		(read_addr2),
                                 .read_data1            (rf_read_data1),
                                 .read_data2            (rf_read_data2)
                                 );

   wire [31:0] debug_total = register_file_A.regs[0];	

   always @(*) begin
      if (mode) begin
	 write_addr = store_addr;
	 write_data = store_data;
	 write_en = 1'b1;
      end else begin
	 write_addr = dest_addr;
	 write_data = alu_result;
	 write_en = 1'b1;
      end
   end // always @ (*)
   
endmodule // processor

과제_3/processor_tb.v
// processor_tb.v
`timescale 1ns/1ps

module processor_tb;
    reg clk, rst_n;
    reg mode;
    reg [2:0] F;
    reg [4:0] read_addr1;
    reg [4:0] read_addr2;
    reg [4:0] dest_addr;
    reg [4:0] store_addr;
    reg [31:0] store_data;

    processor processor_A(/*AUTOINST*/
			  // Inputs
			  .clk			(clk),
			  .rst_n		(rst_n),
			  .mode			(mode),
			  .F			(F[2:0]),
			  .read_addr1		(read_addr1[4:0]),
			  .read_addr2		(read_addr2[4:0]),
			  .dest_addr		(dest_addr[4:0]),
			  .store_addr		(store_addr[4:0]),
			  .store_data		(store_data[31:0]));

    initial begin
        clk = 0;
        forever #5 clk = ~clk;
    end
    
    initial begin
        $dumpfile("processor_tb.vcd");
        $dumpvars(0, processor_tb);
    end

    integer i;
    initial begin
    
        rst_n = 0;
        mode = 1'b0;
        F = 3'b000;
        read_addr1 = 5'd0;
        read_addr2 = 5'd0;
        dest_addr = 5'd0;
        store_addr = 5'd0;
        store_data = 32'd0;

        #12;
        rst_n = 1;
        mode = 1'b1;

        for (i = 0; i < 10; i = i + 1) begin
            store_addr = i + 1; 
            store_data = i + 5;  
            #10;
        end

        for (i = 0; i < 10; i = i + 1) begin
            store_addr = i + 11;      
            store_data = 15 - i;   
            #10;
        end

        mode = 1'b0; 

        for (i = 0; i < 10; i = i + 1) begin
            read_addr1 = i + 1;   
            read_addr2 = i + 11;     
            F = 3'b100;              
            dest_addr = 5'd21;        
            #10;

            read_addr1 = 5'd0;     
            read_addr2 = 5'd21;    
            F = 3'b000;              
            dest_addr = 5'd0;     
            #10;
        end // for (i = 0; i < 10; i = i + 1)

        #50; 
        $finish;
    end // initial begin
   
endmodule // processor_tb

과제_3/processor_tb.vcd
$date
	Thu Apr 10 18:49:40 2025
$end
$version
	Icarus Verilog
$end
$timescale
	1ps
$end
$scope module processor_tb $end
$var reg 3 ! F [2:0] $end
$var reg 1 " clk $end
$var reg 5 # dest_addr [4:0] $end
$var reg 1 $ mode $end
$var reg 5 % read_addr1 [4:0] $end
$var reg 5 & read_addr2 [4:0] $end
$var reg 1 ' rst_n $end
$var reg 5 ( store_addr [4:0] $end
$var reg 32 ) store_data [31:0] $end
$var integer 32 * i [31:0] $end
$scope module processor_A $end
$var wire 3 + F [2:0] $end
$var wire 32 , alu_a [31:0] $end
$var wire 32 - alu_b [31:0] $end
$var wire 1 " clk $end
$var wire 32 . debug_total [31:0] $end
$var wire 5 / dest_addr [4:0] $end
$var wire 1 $ mode $end
$var wire 5 0 read_addr1 [4:0] $end
$var wire 5 1 read_addr2 [4:0] $end
$var wire 1 ' rst_n $end
$var wire 5 2 store_addr [4:0] $end
$var wire 32 3 store_data [31:0] $end
$var wire 32 4 rf_read_data2 [31:0] $end
$var wire 32 5 rf_read_data1 [31:0] $end
$var wire 32 6 alu_result [31:0] $end
$var reg 5 7 write_addr [4:0] $end
$var reg 32 8 write_data [31:0] $end
$var reg 1 9 write_en $end
$scope module alu_A $end
$var wire 3 : F [2:0] $end
$var wire 32 ; a [31:0] $end
$var wire 32 < b [31:0] $end
$var reg 32 = result [31:0] $end
$upscope $end
$scope module register_file_A $end
$var wire 1 " clk $end
$var wire 5 > read_addr1 [4:0] $end
$var wire 5 ? read_addr2 [4:0] $end
$var wire 32 @ read_data1 [31:0] $end
$var wire 32 A read_data2 [31:0] $end
$var wire 1 ' rst_n $end
$var wire 5 B write_addr [4:0] $end
$var wire 32 C write_data [31:0] $end
$var wire 1 9 write_en $end
$var integer 32 D i [31:0] $end
$upscope $end
$upscope $end
$upscope $end
$enddefinitions $end
$comment Show the parameter values. $end
$dumpall
$end
#0
$dumpvars
b100000 D
b0 C
b0 B
b0 A
b0 @
b0 ?
b0 >
b0 =
b0 <
b0 ;
b0 :
19
b0 8
b0 7
b0 6
b0 5
b0 4
b0 3
b0 2
b0 1
b0 0
b0 /
b0 .
b0 -
b0 ,
b0 +
bx *
b0 )
b0 (
0'
b0 &
b0 %
0$
b0 #
0"
b0 !
$end
#5000
b100000 D
1"
#10000
0"
#12000
b101 8
b101 C
b1 7
b1 B
b101 )
b101 3
b1 (
b1 2
b0 *
1$
1'
#15000
1"
#20000
0"
#22000
b110 8
b110 C
b10 7
b10 B
b110 )
b110 3
b10 (
b10 2
b1 *
#25000
1"
#30000
0"
#32000
b111 8
b111 C
b11 7
b11 B
b111 )
b111 3
b11 (
b11 2
b10 *
#35000
1"
#40000
0"
#42000
b1000 8
b1000 C
b100 7
b100 B
b1000 )
b1000 3
b100 (
b100 2
b11 *
#45000
1"
#50000
0"
#52000
b1001 8
b1001 C
b101 7
b101 B
b1001 )
b1001 3
b101 (
b101 2
b100 *
#55000
1"
#60000
0"
#62000
b1010 8
b1010 C
b110 7
b110 B
b1010 )
b1010 3
b110 (
b110 2
b101 *
#65000
1"
#70000
0"
#72000
b1011 8
b1011 C
b111 7
b111 B
b1011 )
b1011 3
b111 (
b111 2
b110 *
#75000
1"
#80000
0"
#82000
b1100 8
b1100 C
b1000 7
b1000 B
b1100 )
b1100 3
b1000 (
b1000 2
b111 *
#85000
1"
#90000
0"
#92000
b1101 8
b1101 C
b1001 7
b1001 B
b1101 )
b1101 3
b1001 (
b1001 2
b1000 *
#95000
1"
#100000
0"
#102000
b1110 8
b1110 C
b1010 7
b1010 B
b1110 )
b1110 3
b1010 (
b1010 2
b1001 *
#105000
1"
#110000
0"
#112000
b1111 8
b1111 C
b1011 7
b1011 B
b1111 )
b1111 3
b1011 (
b1011 2
b0 *
#115000
1"
#120000
0"
#122000
b1110 8
b1110 C
b1100 7
b1100 B
b1110 )
b1110 3
b1100 (
b1100 2
b1 *
#125000
1"
#130000
0"
#132000
b1101 8
b1101 C
b1101 7
b1101 B
b1101 )
b1101 3
b1101 (
b1101 2
b10 *
#135000
1"
#140000
0"
#142000
b1100 8
b1100 C
b1110 7
b1110 B
b1100 )
b1100 3
b1110 (
b1110 2
b11 *
#145000
1"
#150000
0"
#152000
b1011 8
b1011 C
b1111 7
b1111 B
b1011 )
b1011 3
b1111 (
b1111 2
b100 *
#155000
1"
#160000
0"
#162000
b1010 8
b1010 C
b10000 7
b10000 B
b1010 )
b1010 3
b10000 (
b10000 2
b101 *
#165000
1"
#170000
0"
#172000
b1001 8
b1001 C
b10001 7
b10001 B
b1001 )
b1001 3
b10001 (
b10001 2
b110 *
#175000
1"
#180000
0"
#182000
b1000 8
b1000 C
b10010 7
b10010 B
b1000 )
b1000 3
b10010 (
b10010 2
b111 *
#185000
1"
#190000
0"
#192000
b111 8
b111 C
b10011 7
b10011 B
b111 )
b111 3
b10011 (
b10011 2
b1000 *
#195000
1"
#200000
0"
#202000
b110 8
b110 C
b10100 7
b10100 B
b110 )
b110 3
b10100 (
b10100 2
b1001 *
#205000
1"
#210000
0"
#212000
b1001011 6
b1001011 =
b1001011 8
b1001011 C
b10101 7
b10101 B
b10101 #
b10101 /
b100 !
b100 +
b100 :
b1111 -
b1111 <
b1111 4
b1111 A
b1011 &
b1011 1
b1011 ?
b101 ,
b101 ;
b101 5
b101 @
b1 %
b1 0
b1 >
0$
b0 *
#215000
1"
#220000
0"
#222000
b0 7
b0 B
b0 #
b0 /
b0 !
b0 +
b0 :
b1001011 -
b1001011 <
b1001011 4
b1001011 A
b10101 &
b10101 1
b10101 ?
b0 ,
b0 ;
b0 5
b0 @
b0 %
b0 0
b0 >
#225000
b10010110 8
b10010110 C
b10010110 6
b10010110 =
b1001011 ,
b1001011 ;
b1001011 5
b1001011 @
b1001011 .
1"
#230000
0"
#232000
b1010100 8
b1010100 C
b10101 7
b10101 B
b1010100 6
b1010100 =
b10101 #
b10101 /
b100 !
b100 +
b100 :
b1110 -
b1110 <
b1110 4
b1110 A
b1100 &
b1100 1
b1100 ?
b110 ,
b110 ;
b110 5
b110 @
b10 %
b10 0
b10 >
b1 *
#235000
1"
#240000
0"
#242000
b10011111 8
b10011111 C
b0 7
b0 B
b10011111 6
b10011111 =
b0 #
b0 /
b0 !
b0 +
b0 :
b1010100 -
b1010100 <
b1010100 4
b1010100 A
b10101 &
b10101 1
b10101 ?
b1001011 ,
b1001011 ;
b1001011 5
b1001011 @
b0 %
b0 0
b0 >
#245000
b11110011 8
b11110011 C
b11110011 6
b11110011 =
b10011111 ,
b10011111 ;
b10011111 5
b10011111 @
b10011111 .
1"
#250000
0"
#252000
b1011011 8
b1011011 C
b10101 7
b10101 B
b1011011 6
b1011011 =
b10101 #
b10101 /
b100 !
b100 +
b100 :
b1101 -
b1101 <
b1101 4
b1101 A
b1101 &
b1101 1
b1101 ?
b111 ,
b111 ;
b111 5
b111 @
b11 %
b11 0
b11 >
b10 *
#255000
1"
#260000
0"
#262000
b11111010 8
b11111010 C
b0 7
b0 B
b11111010 6
b11111010 =
b0 #
b0 /
b0 !
b0 +
b0 :
b1011011 -
b1011011 <
b1011011 4
b1011011 A
b10101 &
b10101 1
b10101 ?
b10011111 ,
b10011111 ;
b10011111 5
b10011111 @
b0 %
b0 0
b0 >
#265000
b101010101 8
b101010101 C
b101010101 6
b101010101 =
b11111010 ,
b11111010 ;
b11111010 5
b11111010 @
b11111010 .
1"
#270000
0"
#272000
b1100000 8
b1100000 C
b10101 7
b10101 B
b1100000 6
b1100000 =
b10101 #
b10101 /
b100 !
b100 +
b100 :
b1100 -
b1100 <
b1100 4
b1100 A
b1110 &
b1110 1
b1110 ?
b1000 ,
b1000 ;
b1000 5
b1000 @
b100 %
b100 0
b100 >
b11 *
#275000
1"
#280000
0"
#282000
b101011010 8
b101011010 C
b0 7
b0 B
b101011010 6
b101011010 =
b0 #
b0 /
b0 !
b0 +
b0 :
b1100000 -
b1100000 <
b1100000 4
b1100000 A
b10101 &
b10101 1
b10101 ?
b11111010 ,
b11111010 ;
b11111010 5
b11111010 @
b0 %
b0 0
b0 >
#285000
b110111010 8
b110111010 C
b110111010 6
b110111010 =
b101011010 ,
b101011010 ;
b101011010 5
b101011010 @
b101011010 .
1"
#290000
0"
#292000
b1100011 8
b1100011 C
b10101 7
b10101 B
b1100011 6
b1100011 =
b10101 #
b10101 /
b100 !
b100 +
b100 :
b1011 -
b1011 <
b1011 4
b1011 A
b1111 &
b1111 1
b1111 ?
b1001 ,
b1001 ;
b1001 5
b1001 @
b101 %
b101 0
b101 >
b100 *
#295000
1"
#300000
0"
#302000
b110111101 8
b110111101 C
b0 7
b0 B
b110111101 6
b110111101 =
b0 #
b0 /
b0 !
b0 +
b0 :
b1100011 -
b1100011 <
b1100011 4
b1100011 A
b10101 &
b10101 1
b10101 ?
b101011010 ,
b101011010 ;
b101011010 5
b101011010 @
b0 %
b0 0
b0 >
#305000
b1000100000 8
b1000100000 C
b1000100000 6
b1000100000 =
b110111101 ,
b110111101 ;
b110111101 5
b110111101 @
b110111101 .
1"
#310000
0"
#312000
b1100100 8
b1100100 C
b10101 7
b10101 B
b1100100 6
b1100100 =
b10101 #
b10101 /
b100 !
b100 +
b100 :
b1010 -
b1010 <
b1010 4
b1010 A
b10000 &
b10000 1
b10000 ?
b1010 ,
b1010 ;
b1010 5
b1010 @
b110 %
b110 0
b110 >
b101 *
#315000
1"
#320000
0"
#322000
b1000100001 8
b1000100001 C
b0 7
b0 B
b1000100001 6
b1000100001 =
b0 #
b0 /
b0 !
b0 +
b0 :
b1100100 -
b1100100 <
b1100100 4
b1100100 A
b10101 &
b10101 1
b10101 ?
b110111101 ,
b110111101 ;
b110111101 5
b110111101 @
b0 %
b0 0
b0 >
#325000
b1010000101 8
b1010000101 C
b1010000101 6
b1010000101 =
b1000100001 ,
b1000100001 ;
b1000100001 5
b1000100001 @
b1000100001 .
1"
#330000
0"
#332000
b1100011 8
b1100011 C
b10101 7
b10101 B
b1100011 6
b1100011 =
b10101 #
b10101 /
b100 !
b100 +
b100 :
b1001 -
b1001 <
b1001 4
b1001 A
b10001 &
b10001 1
b10001 ?
b1011 ,
b1011 ;
b1011 5
b1011 @
b111 %
b111 0
b111 >
b110 *
#335000
1"
#340000
0"
#342000
b1010000100 8
b1010000100 C
b0 7
b0 B
b1010000100 6
b1010000100 =
b0 #
b0 /
b0 !
b0 +
b0 :
b1100011 -
b1100011 <
b1100011 4
b1100011 A
b10101 &
b10101 1
b10101 ?
b1000100001 ,
b1000100001 ;
b1000100001 5
b1000100001 @
b0 %
b0 0
b0 >
#345000
b1011100111 8
b1011100111 C
b1011100111 6
b1011100111 =
b1010000100 ,
b1010000100 ;
b1010000100 5
b1010000100 @
b1010000100 .
1"
#350000
0"
#352000
b1100000 8
b1100000 C
b10101 7
b10101 B
b1100000 6
b1100000 =
b10101 #
b10101 /
b100 !
b100 +
b100 :
b1000 -
b1000 <
b1000 4
b1000 A
b10010 &
b10010 1
b10010 ?
b1100 ,
b1100 ;
b1100 5
b1100 @
b1000 %
b1000 0
b1000 >
b111 *
#355000
1"
#360000
0"
#362000
b1011100100 8
b1011100100 C
b0 7
b0 B
b1011100100 6
b1011100100 =
b0 #
b0 /
b0 !
b0 +
b0 :
b1100000 -
b1100000 <
b1100000 4
b1100000 A
b10101 &
b10101 1
b10101 ?
b1010000100 ,
b1010000100 ;
b1010000100 5
b1010000100 @
b0 %
b0 0
b0 >
#365000
b1101000100 8
b1101000100 C
b1101000100 6
b1101000100 =
b1011100100 ,
b1011100100 ;
b1011100100 5
b1011100100 @
b1011100100 .
1"
#370000
0"
#372000
b1011011 8
b1011011 C
b10101 7
b10101 B
b1011011 6
b1011011 =
b10101 #
b10101 /
b100 !
b100 +
b100 :
b111 -
b111 <
b111 4
b111 A
b10011 &
b10011 1
b10011 ?
b1101 ,
b1101 ;
b1101 5
b1101 @
b1001 %
b1001 0
b1001 >
b1000 *
#375000
1"
#380000
0"
#382000
b1100111111 8
b1100111111 C
b0 7
b0 B
b1100111111 6
b1100111111 =
b0 #
b0 /
b0 !
b0 +
b0 :
b1011011 -
b1011011 <
b1011011 4
b1011011 A
b10101 &
b10101 1
b10101 ?
b1011100100 ,
b1011100100 ;
b1011100100 5
b1011100100 @
b0 %
b0 0
b0 >
#385000
b1110011010 8
b1110011010 C
b1110011010 6
b1110011010 =
b1100111111 ,
b1100111111 ;
b1100111111 5
b1100111111 @
b1100111111 .
1"
#390000
0"
#392000
b1010100 8
b1010100 C
b10101 7
b10101 B
b1010100 6
b1010100 =
b10101 #
b10101 /
b100 !
b100 +
b100 :
b110 -
b110 <
b110 4
b110 A
b10100 &
b10100 1
b10100 ?
b1110 ,
b1110 ;
b1110 5
b1110 @
b1010 %
b1010 0
b1010 >
b1001 *
#395000
1"
#400000
0"
#402000
b1110010011 8
b1110010011 C
b0 7
b0 B
b1110010011 6
b1110010011 =
b0 #
b0 /
b0 !
b0 +
b0 :
b1010100 -
b1010100 <
b1010100 4
b1010100 A
b10101 &
b10101 1
b10101 ?
b1100111111 ,
b1100111111 ;
b1100111111 5
b1100111111 @
b0 %
b0 0
b0 >
#405000
b1111100111 8
b1111100111 C
b1111100111 6
b1111100111 =
b1110010011 ,
b1110010011 ;
b1110010011 5
b1110010011 @
b1110010011 .
1"
#410000
0"
#412000
b1010 *
#415000
b10000111011 8
b10000111011 C
b10000111011 6
b10000111011 =
b1111100111 ,
b1111100111 ;
b1111100111 5
b1111100111 @
b1111100111 .
1"
#420000
0"
#425000
b10010001111 8
b10010001111 C
b10010001111 6
b10010001111 =
b10000111011 ,
b10000111011 ;
b10000111011 5
b10000111011 @
b10000111011 .
1"
#430000
0"
#435000
b10011100011 8
b10011100011 C
b10011100011 6
b10011100011 =
b10010001111 ,
b10010001111 ;
b10010001111 5
b10010001111 @
b10010001111 .
1"
#440000
0"
#445000
b10100110111 8
b10100110111 C
b10100110111 6
b10100110111 =
b10011100011 ,
b10011100011 ;
b10011100011 5
b10011100011 @
b10011100011 .
1"
#450000
0"
#455000
b10110001011 8
b10110001011 C
b10110001011 6
b10110001011 =
b10100110111 ,
b10100110111 ;
b10100110111 5
b10100110111 @
b10100110111 .
1"
